ragavi/__init__.py
ragavi/ragavi.py
ragavi/bin/ragavi
ragavi-0.0.3.data/scripts/ragavi
ragavi-0.0.3.dist-info/DESCRIPTION.rst
ragavi-0.0.3.dist-info/METADATA
ragavi-0.0.3.dist-info/RECORD
ragavi-0.0.3.dist-info/WHEEL
ragavi-0.0.3.dist-info/metadata.json
ragavi-0.0.3.dist-info/top_level.txt
